{
  "HALProvider": {
    "Other Devices": {
      "window": {
        "visible": false
      }
    }
  },
  "NTProvider": {
    "types": {
      "/FMSInfo": "FMSInfo",
      "/SmartDashboard/Autonomous": "String Chooser",
      "/SmartDashboard/Climber": "Mechanism2d",
      "/SmartDashboard/Field": "Field2d",
      "/SmartDashboard/Lift Mechanism": "Mechanism2d"
    },
    "windows": {
      "/FMSInfo": {
        "window": {
          "visible": true
        }
      },
      "/SmartDashboard/Autonomous": {
        "window": {
          "visible": true
        }
      },
      "/SmartDashboard/Climber": {
        "window": {
          "visible": true
        }
      },
      "/SmartDashboard/Field": {
        "bottom": 1476,
        "height": 8.210550308227539,
        "left": 150,
        "right": 2961,
        "top": 79,
        "width": 16.541748046875,
        "window": {
          "visible": true
        }
      },
      "/SmartDashboard/Lift Mechanism": {
        "window": {
          "visible": true
        }
      }
    }
  },
  "NetworkTables": {
    "SmartDashboard": {
      "Swerve": {
        "Modules": {
          "Back Left": {
            "open": true
          },
          "open": true
        },
        "double[]##v_/SmartDashboard/Swerve/Desired Speeds": {
          "open": true
        },
        "double[]##v_/SmartDashboard/Swerve/Previous Setpoint": {
          "open": true
        },
        "open": true
      },
      "open": true
    },
    "combined": true
  },
  "NetworkTables Info": {
    "Clients": {
      "open": true
    },
    "Server": {
      "open": true
    },
    "visible": true
  }
}
